postproxy/__init__.py
postproxy/postproxy.py
postproxy-0.1.dist-info/METADATA
postproxy-0.1.dist-info/WHEEL
postproxy-0.1.dist-info/entry_points.txt
postproxy-0.1.dist-info/top_level.txt
postproxy-0.1.dist-info/RECORD
